ChangeLog.rst
LICENSE
MANIFEST.in
README.md
pyproject.toml
setup.py
examples/atom_reader.c
examples/ligands_water.py
examples/locations.py
examples/mini.cif
examples/non_standard_residues.py
examples/simple-docking.py
examples/simple.pdb
examples/stream_parser.py
examples/token_reader.py
examples/validate_pdb_ihm.py
ihm/__init__.py
ihm/analysis.py
ihm/citations.py
ihm/cross_linkers.py
ihm/dataset.py
ihm/dictionary.py
ihm/dumper.py
ihm/flr.py
ihm/format.py
ihm/format_bcif.py
ihm/geometry.py
ihm/location.py
ihm/metadata.py
ihm/model.py
ihm/multi_state_scheme.py
ihm/protocol.py
ihm/reader.py
ihm/reference.py
ihm/report.py
ihm/representation.py
ihm/restraint.py
ihm/source.py
ihm/startmodel.py
ihm/test.py
ihm.egg-info/PKG-INFO
ihm.egg-info/SOURCES.txt
ihm.egg-info/dependency_links.txt
ihm.egg-info/requires.txt
ihm.egg-info/top_level.txt
ihm/util/__init__.py
ihm/util/make_mmcif.py
src/cmp.c
src/cmp.h
src/ihm_format.c
src/ihm_format.h
src/ihm_format.i
src/ihm_format_wrap_2.8.c
test/test_analysis.py
test/test_citations.py
test/test_cross_linkers.py
test/test_dataset.py
test/test_dictionary.py
test/test_dumper.py
test/test_edit.py
test/test_examples.py
test/test_flr.py
test/test_format.py
test/test_format_bcif.py
test/test_geometry.py
test/test_location.py
test/test_main.py
test/test_make_mmcif.py
test/test_metadata.py
test/test_model.py
test/test_multi_state_scheme.py
test/test_protocol.py
test/test_reader.py
test/test_reference.py
test/test_report.py
test/test_representation.py
test/test_restraint.py
test/test_startmodel.py
test/test_test.py
test/test_util.py