Metadata-Version: 2.4
Name: ihm
Version: 2.8
Summary: Package for handling IHM mmCIF and BinaryCIF files
Home-page: https://github.com/ihmwg/python-ihm
Author: Ben Webb
Author-email: benmwebb@gmail.com
License: MIT
Classifier: Programming Language :: Python :: 3
Classifier: Operating System :: OS Independent
Classifier: Intended Audience :: Science/Research
Classifier: Topic :: Scientific/Engineering
License-File: LICENSE
Requires-Dist: msgpack
Dynamic: author
Dynamic: author-email
Dynamic: classifier
Dynamic: description
Dynamic: description-content-type
Dynamic: home-page
Dynamic: license
Dynamic: license-file
Dynamic: requires-dist
Dynamic: summary
